xiaozhi_sdk/__init__.py
xiaozhi_sdk/__main__.py
xiaozhi_sdk/config.py
xiaozhi_sdk/data.py
xiaozhi_sdk/iot.py
xiaozhi_sdk/mcp.py
xiaozhi_sdk/opus.py
xiaozhi_sdk/utils.py
xiaozhi_sdk-1.0.0.dist-info/licenses/LICENSE
xiaozhi_sdk-1.0.0.dist-info/METADATA
xiaozhi_sdk-1.0.0.dist-info/WHEEL
xiaozhi_sdk-1.0.0.dist-info/top_level.txt
xiaozhi_sdk-1.0.0.dist-info/RECORD
