Metadata-Version: 2.4
Name: xiaozhi-sdk
Version: 1.0.0
Summary: 一个用于连接和控制小智智能设备的Python SDK，支持实时音频通信、MCP工具集成和设备管理功能。
Home-page: https://github.com/dairoot/xiaozhi-sdk
Author: dairoot
Author-email: 623815825@qq.com
Classifier: Programming Language :: Python :: 3
Classifier: License :: OSI Approved :: MIT License
Classifier: Operating System :: OS Independent
Requires-Python: >=3.8
License-File: LICENSE
Requires-Dist: numpy
Requires-Dist: websockets
Requires-Dist: aiohttp
Requires-Dist: av
Requires-Dist: opuslib
Requires-Dist: requests
Requires-Dist: sounddevice
Requires-Dist: python-socks
Dynamic: author
Dynamic: author-email
Dynamic: classifier
Dynamic: description
Dynamic: description-content-type
Dynamic: home-page
Dynamic: license-file
Dynamic: requires-dist
Dynamic: requires-python
Dynamic: summary
